asqlorm/__init__.py
asqlorm/generator/main.py
asqlorm/models.py
asqlorm/sql/sql_alchemy.py
asqlorm/utils.py
asqlorm-0.9.5.dist-info/METADATA
asqlorm-0.9.5.dist-info/WHEEL
asqlorm-0.9.5.dist-info/RECORD
